pyBridgeLD/__init__.py
pyBridgeLD/geometry.py
pyBridgeLD/load_distribution.py
pyBridgeLD/traffic_load.py
pybridgeld-0.1.3.dist-info/LICENSE
pybridgeld-0.1.3.dist-info/WHEEL
pybridgeld-0.1.3.dist-info/METADATA
pybridgeld-0.1.3.dist-info/RECORD
