Metadata-Version: 2.1
Name: pyBridgeLD
Version: 0.1.3
Summary: pyBridgeLD --- Python Bridge Load Distribution 
Author-email: Rocco Raimo <software@ingraimo.simplelogin.com>
Classifier: License :: OSI Approved :: MIT License
Requires-Dist: pandas
Requires-Dist: plotly
Project-URL: Home, https://github.com/RoccoRaimo/pyBridgeLD
